ovos_skill_number_facts/LICENSE
ovos_skill_number_facts/MANIFEST.in
ovos_skill_number_facts/README.md
ovos_skill_number_facts/__init__.py
ovos_skill_number_facts/requirements.txt
ovos_skill_number_facts/version.py
ovos_skill_number_facts/locale/ca-es/Numbers.voc
ovos_skill_number_facts/locale/ca-es/api.voc
ovos_skill_number_facts/locale/ca-es/date_indicator.voc
ovos_skill_number_facts/locale/ca-es/fact.voc
ovos_skill_number_facts/locale/ca-es/math.voc
ovos_skill_number_facts/locale/ca-es/random.voc
ovos_skill_number_facts/locale/ca-es/skill.json
ovos_skill_number_facts/locale/ca-es/year.voc
ovos_skill_number_facts/locale/da-dk/Numbers.voc
ovos_skill_number_facts/locale/da-dk/api.voc
ovos_skill_number_facts/locale/da-dk/date_indicator.voc
ovos_skill_number_facts/locale/da-dk/fact.voc
ovos_skill_number_facts/locale/da-dk/math.voc
ovos_skill_number_facts/locale/da-dk/random.voc
ovos_skill_number_facts/locale/da-dk/skill.json
ovos_skill_number_facts/locale/da-dk/year.voc
ovos_skill_number_facts/locale/de-de/Numbers.voc
ovos_skill_number_facts/locale/de-de/api.voc
ovos_skill_number_facts/locale/de-de/date_indicator.voc
ovos_skill_number_facts/locale/de-de/fact.voc
ovos_skill_number_facts/locale/de-de/math.voc
ovos_skill_number_facts/locale/de-de/random.voc
ovos_skill_number_facts/locale/de-de/skill.json
ovos_skill_number_facts/locale/de-de/year.voc
ovos_skill_number_facts/locale/en-us/Numbers.voc
ovos_skill_number_facts/locale/en-us/api.voc
ovos_skill_number_facts/locale/en-us/date_indicator.voc
ovos_skill_number_facts/locale/en-us/fact.voc
ovos_skill_number_facts/locale/en-us/math.voc
ovos_skill_number_facts/locale/en-us/random.voc
ovos_skill_number_facts/locale/en-us/skill.json
ovos_skill_number_facts/locale/en-us/year.voc
ovos_skill_number_facts/locale/eu/Numbers.voc
ovos_skill_number_facts/locale/eu/api.voc
ovos_skill_number_facts/locale/eu/date_indicator.voc
ovos_skill_number_facts/locale/eu/fact.voc
ovos_skill_number_facts/locale/eu/math.voc
ovos_skill_number_facts/ovos_skill_number_facts.egg-info/PKG-INFO
ovos_skill_number_facts/ovos_skill_number_facts.egg-info/SOURCES.txt
ovos_skill_number_facts/ovos_skill_number_facts.egg-info/dependency_links.txt
ovos_skill_number_facts/ovos_skill_number_facts.egg-info/entry_points.txt
ovos_skill_number_facts/ovos_skill_number_facts.egg-info/requires.txt
ovos_skill_number_facts/ovos_skill_number_facts.egg-info/top_level.txt
ovos_skill_number_facts-0.1.12.dist-info/LICENSE
ovos_skill_number_facts-0.1.12.dist-info/METADATA
ovos_skill_number_facts-0.1.12.dist-info/WHEEL
ovos_skill_number_facts-0.1.12.dist-info/entry_points.txt
ovos_skill_number_facts-0.1.12.dist-info/top_level.txt
ovos_skill_number_facts-0.1.12.dist-info/RECORD
