Metadata-Version: 2.1
Name: ovos-skill-number-facts
Version: 0.1.12
Summary: NumbersSkill
Home-page: https://github.com/OVOSHatchery/ovos-skill-number-facts
Author: OpenVoiceOS
Author-email: jarbasai@mailfence.com
License: Apache2.0
Keywords: ovos skill plugin
License-File: LICENSE
Requires-Dist: ovos-workshop<8.0.0,>=0.0.15
Requires-Dist: ovos-date-parser<1.0.0,>=0.0.1
Requires-Dist: ovos-number-parser<1.0.0,>=0.0.1
